{
    "wallpaper": "/home/bee/Pictures/Big-Sur/Big Sur/wwaves.jpg",

    "special": {
        "background": "#1b1d20",
        "foreground": "#b0b9c2",
        "cursor": "#b0b9c2"
    },
    "colors": {
        "color0": "#191b1d",
        "color1": "#b77b59",
        "color2": "#486050",
        "color3": "#a08237",
        "color4": "#1c4655",
        "color5": "#585e7e",
        "color6": "#346b63",
        "color7": "#868b8f",
        "color8": "#7b8187",
        "color9": "#bd8667",
        "color10": "#60896e",
        "color11": "#ceaf62",
        "color12": "#699bb7",
        "color13": "#7f85a9",
        "color14": "#6e9c95",
        "color15": "#b0b9c2"
    }
}
